dd_core/__init__.py
dd_core/py.typed
dd_core/dataflow/__init__.py
dd_core/dataflow/base.py
dd_core/dataflow/common.py
dd_core/dataflow/custom.py
dd_core/dataflow/custom_serialize.py
dd_core/dataflow/parallel_map.py
dd_core/dataflow/serialize.py
dd_core/dataflow/stats.py
dd_core/datapoint/__init__.py
dd_core/datapoint/annotation.py
dd_core/datapoint/box.py
dd_core/datapoint/convert.py
dd_core/datapoint/image.py
dd_core/datapoint/view.py
dd_core/mapper/__init__.py
dd_core/mapper/cats.py
dd_core/mapper/cocostruct.py
dd_core/mapper/d2struct.py
dd_core/mapper/hfstruct.py
dd_core/mapper/laylmstruct.py
dd_core/mapper/maputils.py
dd_core/mapper/match.py
dd_core/mapper/misc.py
dd_core/mapper/nms.py
dd_core/mapper/pascalstruct.py
dd_core/mapper/prodigystruct.py
dd_core/mapper/pubstruct.py
dd_core/mapper/wandbstruct.py
dd_core/mapper/xfundstruct.py
dd_core/utils/__init__.py
dd_core/utils/concurrency.py
dd_core/utils/context.py
dd_core/utils/develop.py
dd_core/utils/env_info.py
dd_core/utils/error.py
dd_core/utils/file_utils.py
dd_core/utils/fs.py
dd_core/utils/identifier.py
dd_core/utils/logger.py
dd_core/utils/metacfg.py
dd_core/utils/object_types.py
dd_core/utils/pdf_utils.py
dd_core/utils/ptutils.py
dd_core/utils/tqdm.py
dd_core/utils/transform.py
dd_core/utils/types.py
dd_core/utils/utils.py
dd_core/utils/viz.py
dd_core-1.0.6.dist-info/METADATA
dd_core-1.0.6.dist-info/WHEEL
dd_core-1.0.6.dist-info/top_level.txt
dd_core-1.0.6.dist-info/RECORD
